pynusmv_tools/__init__.py
pynusmv_tools/compare.py
pynusmv_tools/diagnosability.py
pynusmv_tools/dotDump.py
pynusmv_tools/arctl/__init__.py
pynusmv_tools/arctl/ast.py
pynusmv_tools/arctl/check.py
pynusmv_tools/arctl/eval.py
pynusmv_tools/arctl/explain.py
pynusmv_tools/arctl/parsing.py
pynusmv_tools/arctl/cmd/__init__.py
pynusmv_tools/arctl/cmd/tlace.py
pynusmv_tools/arctl/cmd/trace.py
pynusmv_tools/arctl/tlace/__init__.py
pynusmv_tools/arctl/tlace/explain.py
pynusmv_tools/arctl/tlace/tlace.py
pynusmv_tools/arctl/tlace/xml.py
pynusmv_tools/atl/__init__.py
pynusmv_tools/atl/ast.py
pynusmv_tools/atl/check.py
pynusmv_tools/atl/eval.py
pynusmv_tools/atl/explain.py
pynusmv_tools/atl/parsing.py
pynusmv_tools/atlkFO/__init__.py
pynusmv_tools/atlkFO/ast.py
pynusmv_tools/atlkFO/check.py
pynusmv_tools/atlkFO/eval.py
pynusmv_tools/atlkFO/parsing.py
pynusmv_tools/atlkPO/__init__.py
pynusmv_tools/atlkPO/check.py
pynusmv_tools/atlkPO/eval.py
pynusmv_tools/atlkPO/evalGen.py
pynusmv_tools/atlkPO/evalGenSI.py
pynusmv_tools/atlkPO/evalMem.py
pynusmv_tools/atlkPO/evalOpt.py
pynusmv_tools/atlkPO/evalPartial.py
pynusmv_tools/atlkPO/evalPartialSI.py
pynusmv_tools/atlkPO/evalSymb.py
pynusmv_tools/atlk_irf/__init__.py
pynusmv_tools/atlk_irf/__main__.py
pynusmv_tools/atlk_irf/backward.py
pynusmv_tools/atlk_irf/common.py
pynusmv_tools/atlk_irf/early.py
pynusmv_tools/atlk_irf/naive.py
pynusmv_tools/atlk_irf/partial.py
pynusmv_tools/atlk_irf/symbolic.py
pynusmv_tools/atlk_irf/utils.py
pynusmv_tools/bmcLTL/__init__.py
pynusmv_tools/bmcLTL/ast.py
pynusmv_tools/bmcLTL/bmc_ltl.py
pynusmv_tools/bmcLTL/bmc_ltl_li.py
pynusmv_tools/bmcLTL/bmc_ltl_py.py
pynusmv_tools/bmcLTL/check.py
pynusmv_tools/bmcLTL/gen.py
pynusmv_tools/bmcLTL/parsing.py
pynusmv_tools/ctl/CTLcheck.py
pynusmv_tools/ctl/__init__.py
pynusmv_tools/ctl/eval.py
pynusmv_tools/ctlk/__init__.py
pynusmv_tools/ctlk/ast.py
pynusmv_tools/ctlk/eval.py
pynusmv_tools/ctlk/explain.py
pynusmv_tools-1.0rc10.dist-info/DESCRIPTION.rst
pynusmv_tools-1.0rc10.dist-info/METADATA
pynusmv_tools-1.0rc10.dist-info/RECORD
pynusmv_tools-1.0rc10.dist-info/WHEEL
pynusmv_tools-1.0rc10.dist-info/entry_points.txt
pynusmv_tools-1.0rc10.dist-info/metadata.json
pynusmv_tools-1.0rc10.dist-info/top_level.txt
